CHANGES.rst
LICENSE.txt
MANIFEST.in
README.rst
build_zoltan.sh
environment.yml
pyproject.toml
requirements.txt
setup.py
docs/requirements.txt
docs/Images/point-partition.png
docs/source/conf.py
docs/source/index.rst
docs/source/overview.rst
docs/source/start.rst
docs/source/reference/index.rst
docs/source/reference/zoltan.rst
pyzoltan/__init__.py
pyzoltan/api.py
pyzoltan.egg-info/PKG-INFO
pyzoltan.egg-info/SOURCES.txt
pyzoltan.egg-info/dependency_links.txt
pyzoltan.egg-info/not-zip-safe
pyzoltan.egg-info/requires.txt
pyzoltan.egg-info/top_level.txt
pyzoltan/core/__init__.pxd
pyzoltan/core/__init__.py
pyzoltan/core/msstdint.h
pyzoltan/core/zoltan.pxd
pyzoltan/core/zoltan.pyx
pyzoltan/core/zoltan_comm.pxd
pyzoltan/core/zoltan_comm.pyx
pyzoltan/core/zoltan_dd.pxd
pyzoltan/core/zoltan_dd.pyx
pyzoltan/core/zoltan_utils.py
pyzoltan/core/tests/3d_partition.py
pyzoltan/core/tests/__init__.py
pyzoltan/core/tests/geometric_partitioner.py
pyzoltan/core/tests/mesh.txt
pyzoltan/core/tests/test_zoltan.py
pyzoltan/core/tests/zcomm.py
pyzoltan/czoltan/__init__.pxd
pyzoltan/czoltan/__init__.py
pyzoltan/czoltan/czoltan.pxd
pyzoltan/czoltan/czoltan_comm.pxd
pyzoltan/czoltan/czoltan_config.pxd
pyzoltan/czoltan/czoltan_dd.pxd
pyzoltan/czoltan/czoltan_types.pxd
pyzoltan/czoltan/mpi-compat.h
pyzoltan/tools/__init__.py
pyzoltan/tools/run_parallel_script.py