Metadata-Version: 2.4
Name: pyzoltan
Version: 1.1.1
Summary: Wrapper for the Zoltan data management library
Home-page: http://github.com/pypr/pyzoltan
Author: PySPH Developers
Author-email: PySPH Developers <pysph-dev@googlegroups.com>
License-Expression: BSD-3-Clause
Project-URL: Documentation, https://pyzoltan.readthedocs.io
Project-URL: Repository, https://github.com/pypr/pyzoltan.git
Project-URL: Issues, https://github.com/pypr/pyzoltan/issues
Keywords: Cython,Zoltan,Dynamic load balancing
Platform: Linux
Platform: Mac OS-X
Platform: Unix
Platform: Windows
Classifier: Development Status :: 5 - Production/Stable
Classifier: Environment :: Console
Classifier: Intended Audience :: Developers
Classifier: Intended Audience :: Science/Research
Classifier: Natural Language :: English
Classifier: Operating System :: MacOS :: MacOS X
Classifier: Operating System :: Microsoft :: Windows
Classifier: Operating System :: POSIX
Classifier: Operating System :: Unix
Classifier: Programming Language :: Python
Classifier: Programming Language :: Python :: 3
Classifier: Topic :: Scientific/Engineering
Classifier: Topic :: Scientific/Engineering :: Physics
Classifier: Topic :: Software Development :: Libraries
License-File: LICENSE.txt
Requires-Dist: numpy
Requires-Dist: mpi4py>=1.2
Provides-Extra: docs
Requires-Dist: sphinx; extra == "docs"
Provides-Extra: tests
Requires-Dist: pytest>=3.0; extra == "tests"
Provides-Extra: dev
Requires-Dist: sphinx; extra == "dev"
Requires-Dist: pytest>=3.0; extra == "dev"
Requires-Dist: cython>3.0; extra == "dev"
Requires-Dist: cyarray; extra == "dev"
Dynamic: author
Dynamic: home-page
Dynamic: license-file
Dynamic: platform
